yamz/__init__.py
yamz/environment.py
yamz/errors.py
yamz/logger.py
yamz/providers/__init__.py
yamz/providers/base.py
yamz/providers/default.py
yamz-0.2.2.dist-info/LICENSE
yamz-0.2.2.dist-info/METADATA
yamz-0.2.2.dist-info/WHEEL
yamz-0.2.2.dist-info/top_level.txt
yamz-0.2.2.dist-info/zip-safe
yamz-0.2.2.dist-info/RECORD
