Metadata-Version: 2.1
Name: yamz
Version: 0.2.2
Summary: An easy way to manage environment specific configuration
Home-page: https://github.com/rhymiz/yamz
Author: Lemuel Boyce
Author-email: lemuelboyce@gmail.com
License: MIT
Platform: UNKNOWN
Classifier: Programming Language :: Python :: 3
Classifier: Programming Language :: Python :: 3.6
Classifier: Programming Language :: Python :: 3.7
Classifier: Programming Language :: Python :: 3.8
Classifier: Programming Language :: Python :: 3.9
Classifier: License :: OSI Approved :: MIT License
Classifier: Operating System :: OS Independent
Requires-Python: >=3.6
